f_icon.py
mac_icon.py
windows_icon.py
f_icon-0.0.4.dist-info/LICENSE
f_icon-0.0.4.dist-info/METADATA
f_icon-0.0.4.dist-info/WHEEL
f_icon-0.0.4.dist-info/top_level.txt
f_icon-0.0.4.dist-info/RECORD
