Metadata-Version: 2.1
Name: f-icon
Version: 0.0.4
Summary: Set image as an icon of the target folder
Home-page: https://github.com/Burve/f-icon
Author: Burve
Author-email: aleksandrs.ivancenko@gmail.com
Classifier: Development Status :: 3 - Alpha
Classifier: Operating System :: MacOS
Classifier: Operating System :: Microsoft :: Windows
Classifier: Programming Language :: Python :: 3
Classifier: Programming Language :: Python :: 3.8
Classifier: License :: OSI Approved :: MIT License
Requires-Python: >=3.8
License-File: LICENSE
Requires-Dist: Pillow >=8.4.0
Requires-Dist: numpy >=1.20.1
Requires-Dist: opencv-python >=4.5.4.56
Requires-Dist: pyobjc-framework-Cocoa >=8.0 ; sys_platform == "darwin"
